setup.py
iqsms/__init__.py
iqsms/client.py
iqsms.egg-info/PKG-INFO
iqsms.egg-info/SOURCES.txt
iqsms.egg-info/dependency_links.txt
iqsms.egg-info/not-zip-safe
iqsms.egg-info/requires.txt
iqsms.egg-info/top_level.txt