Metadata-Version: 1.0
Name: iqsms
Version: 0.1.1
Summary: IQsms.ru client
Home-page: https://github.com/kazhuravlev/iqsms
Author: Kirill Zhuravlev
Author-email: kazhuravlev@fastmail.com
License: The MIT License (MIT)
Platform: UNKNOWN
